{
  "format": 2,
  "id": "boon-native-handoff-v2",
  "aggregate": "verify-all",
  "aggregate_output": "target/reports/report-v2/verify-all.json",
  "aggregate_byte_limit": 262144,
  "gates": [
    {
      "order": 0,
      "gate": "architecture",
      "verifier": "verify-architecture",
      "runner": "architecture",
      "output": "target/reports/report-v2/architecture.json",
      "byte_limit": 262144,
      "sidecar_byte_limit": 0
    },
    {
      "order": 1,
      "gate": "counter-dev",
      "verifier": "verify-counter-dev",
      "runner": "native-product",
      "output": "target/reports/report-v2/counter-dev.json",
      "byte_limit": 262144,
      "sidecar_byte_limit": 67108864,
      "profile": {
        "id": "native-click-switch-v1",
        "arguments": [
          { "flag": "--harness", "value": "timed" },
          { "flag": "--example", "value": "counter" },
          { "flag": "--visible-mode", "value": "click" },
          { "flag": "--visible-samples", "value": "120" },
          { "flag": "--alternate-target", "value": "none" },
          { "flag": "--selection-samples", "value": "0" },
          { "flag": "--scroll-samples", "value": "0" },
          { "flag": "--switch-samples", "value": "23" }
        ],
        "measurements": [
          "callback-to-host-event",
          "warm-visible-interaction",
          "example-switch-acknowledgement",
          "example-switch-final-preview"
        ]
      }
    },
    {
      "order": 2,
      "gate": "todomvc-physical",
      "verifier": "verify-todomvc-physical",
      "runner": "native-product",
      "output": "target/reports/report-v2/todomvc-physical.json",
      "byte_limit": 262144,
      "sidecar_byte_limit": 67108864,
      "profile": {
        "id": "native-hover-v1",
        "arguments": [
          { "flag": "--harness", "value": "timed" },
          { "flag": "--example", "value": "todo_mvc_physical" },
          { "flag": "--visible-mode", "value": "hover" },
          { "flag": "--visible-samples", "value": "120" },
          { "flag": "--alternate-target", "value": "any" },
          { "flag": "--selection-samples", "value": "0" },
          { "flag": "--scroll-samples", "value": "0" },
          { "flag": "--switch-samples", "value": "0" }
        ],
        "measurements": [
          "callback-to-host-event",
          "warm-visible-interaction"
        ]
      }
    },
    {
      "order": 3,
      "gate": "cells",
      "verifier": "verify-cells",
      "runner": "native-product",
      "output": "target/reports/report-v2/cells.json",
      "byte_limit": 262144,
      "sidecar_byte_limit": 67108864,
      "profile": {
        "id": "native-selection-scroll-v1",
        "arguments": [
          { "flag": "--harness", "value": "timed" },
          { "flag": "--example", "value": "cells" },
          { "flag": "--visible-mode", "value": "hover" },
          { "flag": "--visible-samples", "value": "120" },
          { "flag": "--alternate-target", "value": "same-source" },
          { "flag": "--selection-samples", "value": "24" },
          { "flag": "--scroll-samples", "value": "148" },
          { "flag": "--switch-samples", "value": "0" }
        ],
        "measurements": [
          "callback-to-host-event",
          "warm-visible-interaction",
          "repeated-selection",
          "warm-scroll"
        ]
      }
    },
    {
      "order": 4,
      "gate": "novywave",
      "verifier": "verify-novywave",
      "runner": "native-product",
      "output": "target/reports/report-v2/novywave.json",
      "byte_limit": 262144,
      "sidecar_byte_limit": 67108864,
      "profile": {
        "id": "native-hover-v1",
        "arguments": [
          { "flag": "--harness", "value": "timed" },
          { "flag": "--example", "value": "novywave" },
          { "flag": "--visible-mode", "value": "hover" },
          { "flag": "--visible-samples", "value": "120" },
          { "flag": "--alternate-target", "value": "any" },
          { "flag": "--selection-samples", "value": "0" },
          { "flag": "--scroll-samples", "value": "0" },
          { "flag": "--switch-samples", "value": "0" }
        ],
        "measurements": [
          "callback-to-host-event",
          "warm-visible-interaction"
        ]
      }
    },
    {
      "order": 5,
      "gate": "persons-pro",
      "verifier": "verify-persons-pro",
      "runner": "native-product",
      "output": "target/reports/report-v2/persons-pro.json",
      "byte_limit": 262144,
      "sidecar_byte_limit": 67108864,
      "profile": {
        "id": "native-local-first-workflow-v2",
        "arguments": [
          { "flag": "--harness", "value": "timed" },
          { "flag": "--example", "value": "persons_pro" },
          { "flag": "--visible-mode", "value": "hover" },
          { "flag": "--visible-samples", "value": "120" },
          { "flag": "--alternate-target", "value": "any" },
          { "flag": "--selection-samples", "value": "0" },
          { "flag": "--scroll-samples", "value": "148" },
          { "flag": "--switch-samples", "value": "0" },
          { "flag": "--profile-benchmark-steps", "value": "valid-edit-preview,corrected-edit-preview" }
        ],
        "measurements": [
          "callback-to-host-event",
          "warm-visible-interaction",
          "warm-scroll"
        ],
        "proof_requirements": {
          "scenario": {
            "path": "examples/persons_pro.scn",
            "semantic_assertions": true
          },
          "budget": {
            "path": "examples/persons_pro.budget.toml",
            "metrics": [
              "keystroke-to-editor-visible-p95",
              "valid-edit-to-preview-visible-p95",
              "valid-edit-to-preview-visible-p99",
              "bounded-starter-source-compile-p95",
              "bounded-starter-source-compile-max",
              "passive-preview-scroll-p95",
              "interaction-frame-block-max",
              "pending-child-artifact-max",
              "pending-program-artifact-store-max",
              "pending-program-artifact-load-max",
              "pending-persistence-artifact-store-max",
              "pending-persistence-artifact-load-max",
              "pending-durable-batch-max",
              "proof-replacement-max",
              "proof-result-drop-max",
              "trusted-parent-rebuilds-per-edit"
            ]
          },
          "state_root": {
            "policy": "launch-scoped-clean",
            "restart_required": true
          },
          "async_lanes": [
            "child-program-compile",
            "persistence-turn",
            "program-artifact-store",
            "program-artifact-load",
            "proof-readback"
          ],
          "native_workflow": {
            "delivery": "kernel-uinput-isolated-seat",
            "scenario_boundary": "kernel-uinput-and-semantic-assertions",
            "capture_method": "app-owned-render-target-readback",
            "durability": "state-changing-steps-acked",
            "steps": [
              "fresh-anonymous-workspace-and-starter-preview",
              "editor-page-down-reveals-caret",
              "editor-selects-all",
              "editor-copies-selection",
              "editor-navigates-to-end",
              "editor-pastes-copy",
              "editor-selects-copy-for-deletion",
              "editor-deletes-selection",
              "valid-edit-preview",
              "invalid-edit-retains-last-valid",
              "diagnostic-focuses-source-location",
              "corrected-edit-preview",
              "immutable-publish",
              "published-child-artifact-visible",
              "invalid-edit-before-failed-publish",
              "failed-publish-preserves-pointer",
              "select-passkey-cancellation",
              "passkey-cancel-preserves-anonymous",
              "select-passkey-registration-failure",
              "passkey-registration-failure-preserves-anonymous",
              "select-passkey-success",
              "first-passkey-protects",
              "select-duplicate-credential",
              "duplicate-credential-is-rejected",
              "restore-passkey-success-mode",
              "second-passkey-same-account",
              "sign-out",
              "select-authentication-cancellation",
              "authentication-cancellation-preserves-sign-out",
              "select-authentication-failure",
              "authentication-failure-preserves-sign-out",
              "select-authentication-success",
              "passkey-sign-in-restores-access",
              "toggle-dark",
              "phone-preview-width",
              "restore-auto-preview-width"
            ],
            "proof_steps": [
              "fresh-anonymous-workspace-and-starter-preview",
              "editor-page-down-reveals-caret",
              "editor-selects-all",
              "editor-copies-selection",
              "editor-navigates-to-end",
              "editor-pastes-copy",
              "editor-deletes-selection",
              "valid-edit-preview",
              "invalid-edit-retains-last-valid",
              "diagnostic-focuses-source-location",
              "corrected-edit-preview",
              "immutable-publish",
              "published-child-artifact-visible",
              "failed-publish-preserves-pointer",
              "passkey-cancel-preserves-anonymous",
              "passkey-registration-failure-preserves-anonymous",
              "first-passkey-protects",
              "duplicate-credential-is-rejected",
              "second-passkey-same-account",
              "authentication-cancellation-preserves-sign-out",
              "authentication-failure-preserves-sign-out",
              "passkey-sign-in-restores-access",
              "phone-preview-width",
              "restore-auto-preview-width"
            ]
          },
          "checkpoints": [
            {
              "id": "fresh-anonymous-workspace",
              "kind": "native-workflow-step",
              "scenario_step": "fresh-anonymous-workspace-and-starter-preview"
            },
            {
              "id": "starter-child-preview",
              "kind": "native-workflow-step",
              "scenario_step": "fresh-anonymous-workspace-and-starter-preview"
            },
            {
              "id": "valid-edit-preview",
              "kind": "native-workflow-step",
              "scenario_step": "valid-edit-preview"
            },
            {
              "id": "invalid-edit-last-valid",
              "kind": "native-workflow-step",
              "scenario_step": "invalid-edit-retains-last-valid"
            },
            {
              "id": "corrected-edit-preview",
              "kind": "native-workflow-step",
              "scenario_step": "corrected-edit-preview"
            },
            {
              "id": "publish-success",
              "kind": "native-workflow-step",
              "scenario_step": "immutable-publish"
            },
            {
              "id": "published-child-visible",
              "kind": "native-workflow-step",
              "scenario_step": "published-child-artifact-visible"
            },
            {
              "id": "publish-failure-preserves-pointer",
              "kind": "native-workflow-step",
              "scenario_step": "failed-publish-preserves-pointer"
            },
            {
              "id": "passkey-cancel-preserves-anonymous",
              "kind": "native-workflow-step",
              "scenario_step": "passkey-cancel-preserves-anonymous"
            },
            {
              "id": "passkey-failure-preserves-anonymous",
              "kind": "native-workflow-step",
              "scenario_step": "passkey-registration-failure-preserves-anonymous"
            },
            {
              "id": "first-passkey-protects",
              "kind": "native-workflow-step",
              "scenario_step": "first-passkey-protects"
            },
            {
              "id": "duplicate-passkey-rejected",
              "kind": "native-workflow-step",
              "scenario_step": "duplicate-credential-is-rejected"
            },
            {
              "id": "second-passkey-same-account",
              "kind": "native-workflow-step",
              "scenario_step": "second-passkey-same-account"
            },
            {
              "id": "authentication-cancel-preserves-sign-out",
              "kind": "native-workflow-step",
              "scenario_step": "authentication-cancellation-preserves-sign-out"
            },
            {
              "id": "authentication-failure-preserves-sign-out",
              "kind": "native-workflow-step",
              "scenario_step": "authentication-failure-preserves-sign-out"
            },
            {
              "id": "sign-out-sign-in",
              "kind": "native-workflow-step",
              "scenario_step": "passkey-sign-in-restores-access"
            },
            {
              "id": "restart-restores-authority",
              "kind": "restart-restore",
              "baseline_checkpoint": "native-auto-preview"
            },
            {
              "id": "responsive-layout-parity",
              "kind": "responsive-layout",
              "baseline_checkpoint": "native-auto-preview",
              "logical_width": 390,
              "navigation_sources": [
                "store.elements.show_preview",
                "store.elements.show_publish",
                "store.elements.show_code"
              ]
            },
            {
              "id": "stale-compile-rejected",
              "kind": "stale-compile-rejection"
            },
            {
              "id": "clear-start-over",
              "kind": "persistence-operation",
              "operation": "cleared-and-started-over"
            },
            {
              "id": "state-exported",
              "kind": "persistence-operation",
              "operation": "exported"
            },
            {
              "id": "corrupt-state-rejected",
              "kind": "persistence-operation",
              "operation": "corruption-rejected"
            },
            {
              "id": "state-import-previewed",
              "kind": "persistence-operation",
              "operation": "import-previewed"
            },
            {
              "id": "state-import-activated",
              "kind": "persistence-operation",
              "operation": "import-activated"
            },
            {
              "id": "schema-migration-activated",
              "kind": "persistence-operation",
              "operation": "migration-activated"
            },
            {
              "id": "native-diagnostic-focus",
              "kind": "native-workflow-step",
              "scenario_step": "diagnostic-focuses-source-location"
            },
            {
              "id": "native-publish",
              "kind": "native-workflow-step",
              "scenario_step": "immutable-publish"
            },
            {
              "id": "native-published-page",
              "kind": "native-workflow-step",
              "scenario_step": "published-child-artifact-visible"
            },
            {
              "id": "native-protect-workspace",
              "kind": "native-workflow-step",
              "scenario_step": "first-passkey-protects"
            },
            {
              "id": "native-sign-in",
              "kind": "native-workflow-step",
              "scenario_step": "passkey-sign-in-restores-access"
            },
            {
              "id": "native-phone-preview",
              "kind": "native-workflow-step",
              "scenario_step": "phone-preview-width"
            },
            {
              "id": "native-auto-preview",
              "kind": "native-workflow-step",
              "scenario_step": "restore-auto-preview-width"
            }
          ]
        }
      }
    },
    {
      "order": 6,
      "gate": "negative",
      "verifier": "verify-negative",
      "runner": "native-product",
      "output": "target/reports/report-v2/negative.json",
      "byte_limit": 262144,
      "sidecar_byte_limit": 0,
      "profile": {
        "id": "bounded-negative-v1",
        "arguments": [
          { "flag": "--harness", "value": "negative" }
        ],
        "measurements": []
      }
    }
  ]
}
